__init__.py
extra.py
main.py
setup.py
smaller.py
test-mew.py
test.py
broken.egg-info/PKG-INFO
broken.egg-info/SOURCES.txt
broken.egg-info/dependency_links.txt
broken.egg-info/top_level.txt