Metadata-Version: 1.0
Name: broken
Version: 0.1
Summary: The broken Python data structure
Home-page: UNKNOWN
Author: CHC
Author-email: channel4040@gmail.com
License: UNKNOWN
Platform: UNKNOWN
